pdf2embeddings/__init__.py
pdf2embeddings/arrange_text.py
pdf2embeddings/embedder.py
pdf2embeddings/json_creator.py
pdf2embeddings/logging.yaml
pdf2embeddings/process_user_queries.py
pdf2embeddings/scraper.py
pdf2embeddings-0.2.8.dist-info/LICENSE
pdf2embeddings-0.2.8.dist-info/METADATA
pdf2embeddings-0.2.8.dist-info/WHEEL
pdf2embeddings-0.2.8.dist-info/top_level.txt
pdf2embeddings-0.2.8.dist-info/RECORD
