Metadata-Version: 2.1
Name: pdf2embeddings
Version: 0.2.8
Summary: NLP tool for scraping text from a corpus of PDF files, embedding the sentences in the text and finding semantically similar sentences to a given search query.
Home-page: https://github.com/moj-analytical-services/airflow-pdf2embeddings
Author: moj-analytical-services
License: MIT
Download-URL: https://pypi.python.org/pypi/pdf2embeddings
Platform: UNKNOWN
Classifier: License :: OSI Approved :: MIT License
Classifier: Programming Language :: Python :: 3
Classifier: Programming Language :: Python :: 3.6
Classifier: Programming Language :: Python :: 3.7
Requires-Python: >=3.6
Requires-Dist: allennlp (==0.9.0)
Requires-Dist: boto3 (~=1.10.34)
Requires-Dist: gensim (==3.8.1)
Requires-Dist: nltk (==3.4.5)
Requires-Dist: numpy (==1.18.2)
Requires-Dist: pandas (==0.25.3)
Requires-Dist: ply (==3.11)
Requires-Dist: pyarrow (==0.16.0)
Requires-Dist: pytest (==5.4.1)
Requires-Dist: scikit-learn (==0.22.1)
Requires-Dist: scipy (==1.4.1)
Requires-Dist: sentence-transformers (==0.2.5.1)
Requires-Dist: slate3k (==0.5.3)
Requires-Dist: typing (==3.7.4.1)
Requires-Dist: tqdm (==4.45.0)
Requires-Dist: s3fs (~=0.4.2)
